printx/__init__.py
printx/printx.py
printx-1.0.1.dist-info/METADATA
printx-1.0.1.dist-info/WHEEL
printx-1.0.1.dist-info/top_level.txt
printx-1.0.1.dist-info/RECORD
