Metadata-Version: 2.1
Name: printx
Version: 1.0.1
Summary: A Python package that provides a convenient print-like function for logging messages with various log levels, making it easy to integrate logging into your projects.
Home-page: https://github.com/phintegrator/printx
Author: Javer Valino
Classifier: Programming Language :: Python :: 3
Classifier: License :: OSI Approved :: MIT License
Classifier: Operating System :: OS Independent
Requires-Python: >=3.6
